pyvrp/GeneticAlgorithm.py
pyvrp/Model.py
pyvrp/PenaltyManager.py
pyvrp/Population.py
pyvrp/ProgressPrinter.py
pyvrp/Result.py
pyvrp/Statistics.py
pyvrp/__init__.py
pyvrp/_pyvrp.cpython-310-x86_64-linux-gnu.so
pyvrp/_pyvrp.pyi
pyvrp/cli.py
pyvrp/constants.py
pyvrp/cpp/CostEvaluator.cpp
pyvrp/cpp/CostEvaluator.h
pyvrp/cpp/DistanceSegment.cpp
pyvrp/cpp/DistanceSegment.h
pyvrp/cpp/DurationSegment.cpp
pyvrp/cpp/DurationSegment.h
pyvrp/cpp/DynamicBitset.cpp
pyvrp/cpp/DynamicBitset.h
pyvrp/cpp/LoadSegment.cpp
pyvrp/cpp/LoadSegment.h
pyvrp/cpp/Matrix.h
pyvrp/cpp/Measure.h
pyvrp/cpp/ProblemData.cpp
pyvrp/cpp/ProblemData.h
pyvrp/cpp/README.md
pyvrp/cpp/RandomNumberGenerator.cpp
pyvrp/cpp/RandomNumberGenerator.h
pyvrp/cpp/Solution.cpp
pyvrp/cpp/Solution.h
pyvrp/cpp/SubPopulation.cpp
pyvrp/cpp/SubPopulation.h
pyvrp/cpp/bindings.cpp
pyvrp/cpp/bindings.h
pyvrp/cpp/crossover/bindings.cpp
pyvrp/cpp/crossover/ordered_crossover.cpp
pyvrp/cpp/crossover/ordered_crossover.h
pyvrp/cpp/crossover/selective_route_exchange.cpp
pyvrp/cpp/crossover/selective_route_exchange.h
pyvrp/cpp/diversity/bindings.cpp
pyvrp/cpp/diversity/broken_pairs_distance.cpp
pyvrp/cpp/diversity/diversity.h
pyvrp/cpp/repair/bindings.cpp
pyvrp/cpp/repair/greedy_repair.cpp
pyvrp/cpp/repair/greedy_repair.h
pyvrp/cpp/repair/nearest_route_insert.cpp
pyvrp/cpp/repair/nearest_route_insert.h
pyvrp/cpp/repair/repair.cpp
pyvrp/cpp/repair/repair.h
pyvrp/cpp/search/Exchange.h
pyvrp/cpp/search/LocalSearch.cpp
pyvrp/cpp/search/LocalSearch.h
pyvrp/cpp/search/LocalSearchOperator.h
pyvrp/cpp/search/Route.cpp
pyvrp/cpp/search/Route.h
pyvrp/cpp/search/SwapRoutes.cpp
pyvrp/cpp/search/SwapRoutes.h
pyvrp/cpp/search/SwapStar.cpp
pyvrp/cpp/search/SwapStar.h
pyvrp/cpp/search/SwapTails.cpp
pyvrp/cpp/search/SwapTails.h
pyvrp/cpp/search/bindings.cpp
pyvrp/cpp/search/primitives.cpp
pyvrp/cpp/search/primitives.h
pyvrp/crossover/__init__.py
pyvrp/crossover/_crossover.cpython-310-x86_64-linux-gnu.so
pyvrp/crossover/_crossover.pyi
pyvrp_load_balancing-0.9.0a0.dist-info/LICENSE.md
pyvrp_load_balancing-0.9.0a0.dist-info/METADATA
pyvrp_load_balancing-0.9.0a0.dist-info/WHEEL
pyvrp_load_balancing-0.9.0a0.dist-info/entry_points.txt
pyvrp_load_balancing-0.9.0a0.dist-info/RECORD
