Metadata-Version: 2.1
Name: pyvrp-load_balancing
Version: 0.9.0a0
Summary: Added load balancing functionality.
Home-page: https://pyvrp.org/
License: MIT
Keywords: vehicle routing problem,hybrid genetic search,metaheuristic
Author: Niels Wouda
Author-email: nielswouda@gmail.com
Requires-Python: >=3.9,<4.0
Classifier: Development Status :: 5 - Production/Stable
Classifier: Intended Audience :: Developers
Classifier: Intended Audience :: Science/Research
Classifier: License :: OSI Approved :: MIT License
Classifier: Programming Language :: Python :: 3
Classifier: Programming Language :: Python :: 3.9
Classifier: Programming Language :: Python :: 3.10
Classifier: Programming Language :: Python :: 3.11
Classifier: Programming Language :: Python :: 3.12
Classifier: Topic :: Scientific/Engineering
Classifier: Topic :: Software Development
Requires-Dist: matplotlib (>=2.2.0)
Requires-Dist: numpy (>=1.15.2) ; python_version < "3.12"
Requires-Dist: numpy (>=1.26.0) ; python_version >= "3.12"
Requires-Dist: tomli (>=2.0.1,<3.0.0)
Requires-Dist: tqdm (>=4.64.1,<5.0.0)
Requires-Dist: vrplib (>=1.2.0,<2.0.0)
Project-URL: Repository, https://github.com/bmorlo/PyVRP_BM_load_balancing
Project-URL: Tracker, https://github.com/PyVRP/PyVRP/issues
